rdbms/__init__.py
rdbms/rdbms.py
rdbms/row_factories.py
rdbms/text_factories.py
rdbms-1.0.2.dist-info/LICENSE
rdbms-1.0.2.dist-info/METADATA
rdbms-1.0.2.dist-info/WHEEL
rdbms-1.0.2.dist-info/top_level.txt
rdbms-1.0.2.dist-info/RECORD
