Metadata-Version: 2.1
Name: rdbms
Version: 1.0.2
Summary: Relational Database Management System
Home-page: https://github.com/dinceraslancom/rdbms
Author: Dincer Aslan
Author-email: dinceraslan.com@gmail.com
License: UNKNOWN
Project-URL: Source, https://github.com/dinceraslancom/rdbms
Platform: UNKNOWN
Classifier: Programming Language :: Python :: 3
Classifier: License :: OSI Approved :: MIT License
Classifier: Operating System :: OS Independent
Requires-Python: >=3.3
License-File: LICENSE
Requires-Dist: simpleitem
